Metadata-Version: 1.1
Name: pychembldb
Version: 0.3.2
Summary: ChEMBLdb interface for Python
Home-page: http://github.com/kzfm/pychembldb
Author: Ohkawa Kazufumi
Author-email: kerolinq@gmail.com
License: MIT
Keywords: chemoinformatics cheminformatics
Platform: UNKNOWN
Classifier: License :: OSI Approved :: MIT License
Classifier: Topic :: Scientific/Engineering :: Chemistry
Classifier: Development Status :: 2 - Pre-Alpha
Classifier: Operating System :: MacOS :: MacOS X
Classifier: Operating System :: POSIX
Classifier: Programming Language :: Python
